{
    "boardData": {
        "setup": {
            "code": "BBBB",
            "round": 1,
            "cryptics": []
        },
        "data": [
            {
                "order": 1,
                "quiz": [
                    {
                        "category": [
                            "Mononymous Spanish Footballers",
                            "Impressionist Painters"
                        ],
                        "clues": [
                            {
                                "title": "Adriàn",
                                "result": "B",
                                "info": ""
                            },
                            {
                                "title": "Ancona",
                                "result": "2",
                                "info": "Ronni Ancona is an impressionist comedian"
                            },
                            {
                                "title": "Leroy",
                                "result": "1",
                                "info": "Louis Leroy is a French art critict, analysing impressionist artworks"
                            },
                            {
                                "title": "Bazille",
                                "result": "B",
                                "info": ""
                            },
                            {
                                "title": "Michu",
                                "result": "A",
                                "info": ""
                            },
                            {
                                "title": "Monet",
                                "result": "A",
                                "info": ""
                            },
                            {
                                "title": "Nayim",
                                "result": "A",
                                "info": ""
                            },
                            {
                                "title": "Pissarro",
                                "result": "B",
                                "info": ""
                            },
                            {
                                "title": "Renoir",
                                "result": "A",
                                "info": ""
                            }
                        ]
                    }
                ]
            },
            {
                "order": 2,
                "quiz": [
                    {
                        "category": [
                            "Nickname of musicians",
                            "Nickname of US Presidents"
                        ],
                        "clues": [
                            {
                                "title": "Mimi",
                                "result": "A",
                                "info": ""
                            },
                            {
                                "title": "No Drama",
                                "result": "B",
                                "info": "Barack Obama"
                            },
                            {
                                "title": "Farmer George",
                                "result": "1",
                                "info": "1760, Surname of King George the Third"
                            },
                            {
                                "title": "The Thin White Duke",
                                "result": "A",
                                "info": ""
                            },
                            {
                                "title": "The Boss",
                                "result": "A",
                                "info": ""
                            },
                            {
                                "title": "The Water Carrier",
                                "result": "2",
                                "info": "Didier Deschamps, a French football manager"
                            },
                            {
                                "title": "Slowhand",
                                "result": "A",
                                "info": ""
                            },
                            {
                                "title": "Old Hickory",
                                "result": "B",
                                "info": "Andrew Jackson"
                            },
                            {
                                "title": "Tricky Dicky",
                                "result": "B",
                                "info": ""
                            }
                        ]
                    }
                ]
            }
        ]
    }
}